agentstr/__init__.py
agentstr/buyer.py
agentstr/buyer.pyi
agentstr/merchant.py
agentstr/merchant.pyi
agentstr/models.py
agentstr/models.pyi
agentstr/nostr.py
agentstr/nostr.pyi
agentstr/py.typed
agentstr-0.1.16.dist-info/LICENSE
agentstr-0.1.16.dist-info/METADATA
agentstr-0.1.16.dist-info/WHEEL
agentstr-0.1.16.dist-info/top_level.txt
agentstr-0.1.16.dist-info/RECORD
