Metadata-Version: 2.2
Name: agentstr
Version: 0.1.16
Summary: Tools for a Nostr agentic ecosystem
Author-email: Synvya <synvya@synvya.com>
License: MIT
Project-URL: Homepage, https://www.synvya.com
Project-URL: Repository, https://github.com/synvya/agentstr
Project-URL: Documentation, https://github.com/synvya/agentstr#readme
Project-URL: BugTracker, https://github.com/synvya/agentstr/issues
Requires-Python: <3.13,>=3.10
License-File: LICENSE
Requires-Dist: agno>=1.1.1
Requires-Dist: openai>=1.50.0
Requires-Dist: nostr_sdk>=0.39.0
Requires-Dist: pydantic>=2.0.0
Provides-Extra: dev
Requires-Dist: pytest>=7.0; extra == "dev"
Requires-Dist: pytest-asyncio>=0.23.5; extra == "dev"
Requires-Dist: black>=23.0; extra == "dev"
Requires-Dist: isort>=5.0; extra == "dev"
Requires-Dist: mypy>=1.0; extra == "dev"
Requires-Dist: pylint>=3.0; extra == "dev"
Provides-Extra: examples
Requires-Dist: python-dotenv>=1.0; extra == "examples"
Requires-Dist: psycopg[binary]>=3.2.5; extra == "examples"
Requires-Dist: sqlalchemy>=2.0.0; extra == "examples"
Requires-Dist: nest-asyncio>=1.6.0; extra == "examples"
Requires-Dist: pgvector>=0.3.6; extra == "examples"
Requires-Dist: fastapi>=0.110.0; extra == "examples"
Requires-Dist: uvicorn>=0.30.0; extra == "examples"
